Metadata-Version: 1.0
Name: zlab
Version: 0.0.1
Summary: Zalando zlab installer
Home-page: https://github.bus.zalan.do/DSI/zlab-cli
Author: Zalando SE
Author-email: zlab-team@gmail.com
License: MIT license
Keywords: zlab
Platform: UNKNOWN
